oodeel/__init__.py
oodeel/datasets/__init__.py
oodeel/datasets/data_handler.py
oodeel/datasets/tf_data_handler.py
oodeel/datasets/torch_data_handler.py
oodeel/datasets/deprecated/DEPRECATED_data_handler.py
oodeel/datasets/deprecated/DEPRECATED_ooddataset.py
oodeel/datasets/deprecated/DEPRECATED_tf_data_handler.py
oodeel/datasets/deprecated/DEPRECATED_torch_data_handler.py
oodeel/datasets/deprecated/__init__.py
oodeel/eval/__init__.py
oodeel/eval/metrics.py
oodeel/eval/plots/__init__.py
oodeel/eval/plots/features.py
oodeel/eval/plots/metrics.py
oodeel/eval/plots/plotly.py
oodeel/extractor/__init__.py
oodeel/extractor/feature_extractor.py
oodeel/extractor/keras_feature_extractor.py
oodeel/extractor/torch_feature_extractor.py
oodeel/methods/__init__.py
oodeel/methods/base.py
oodeel/methods/dknn.py
oodeel/methods/energy.py
oodeel/methods/entropy.py
oodeel/methods/gen.py
oodeel/methods/gram.py
oodeel/methods/mahalanobis.py
oodeel/methods/mls.py
oodeel/methods/odin.py
oodeel/methods/rmds.py
oodeel/methods/she.py
oodeel/methods/vim.py
oodeel/preprocess/__init__.py
oodeel/preprocess/tf_preprocess.py
oodeel/preprocess/torch_preprocess.py
oodeel/types/__init__.py
oodeel/utils/__init__.py
oodeel/utils/general_utils.py
oodeel/utils/operator.py
oodeel/utils/tf_operator.py
oodeel/utils/tf_training_tools.py
oodeel/utils/torch_operator.py
oodeel/utils/torch_training_tools.py
oodeel-0.3.0.dist-info/licenses/LICENSE
tests/__init__.py
tests/tools_operator.py
tests/tests_tensorflow/__init__.py
tests/tests_tensorflow/tf_methods_utils.py
tests/tests_tensorflow/tools_tf.py
tests/tests_torch/__init__.py
tests/tests_torch/tools_torch.py
tests/tests_torch/torch_methods_utils.py
oodeel-0.3.0.dist-info/METADATA
oodeel-0.3.0.dist-info/WHEEL
oodeel-0.3.0.dist-info/top_level.txt
oodeel-0.3.0.dist-info/RECORD
