Metadata-Version: 2.4
Name: oodeel
Version: 0.3.0
Summary: Simple, compact, and hackable post-hoc deep OOD detection for alreadytrained tensorflow or pytorch image classifiers.
Author: DEEL Core Team
Author-email: paul.novello@irt-saintexupery.com
Classifier: Programming Language :: Python
Classifier: Programming Language :: Python :: 3
Classifier: Programming Language :: Python :: 3.7
Classifier: Programming Language :: Python :: 3.8
Classifier: Programming Language :: Python :: 3.9
Classifier: Programming Language :: Python :: 3.10
License-File: LICENSE
Requires-Dist: faiss_cpu
Requires-Dist: numpy
Requires-Dist: scikit_learn
Requires-Dist: scipy
Requires-Dist: setuptools
Requires-Dist: matplotlib
Requires-Dist: pandas
Requires-Dist: seaborn
Requires-Dist: plotly
Requires-Dist: tqdm
Provides-Extra: dev
Requires-Dist: mypy; extra == "dev"
Requires-Dist: ipywidgets; extra == "dev"
Requires-Dist: mkdocs-jupyter; extra == "dev"
Requires-Dist: mkdocstrings-python; extra == "dev"
Requires-Dist: flake8; extra == "dev"
Requires-Dist: setuptools; extra == "dev"
Requires-Dist: pre-commit; extra == "dev"
Requires-Dist: tox; extra == "dev"
Requires-Dist: black; extra == "dev"
Requires-Dist: ruff; extra == "dev"
Requires-Dist: ipython; extra == "dev"
Requires-Dist: ipykernel; extra == "dev"
Requires-Dist: pytest; extra == "dev"
Requires-Dist: pylint; extra == "dev"
Requires-Dist: mypy; extra == "dev"
Requires-Dist: mkdocs; extra == "dev"
Requires-Dist: mkdocs-material; extra == "dev"
Requires-Dist: mkdocstrings; extra == "dev"
Requires-Dist: mknotebooks; extra == "dev"
Requires-Dist: mike; extra == "dev"
Requires-Dist: bump2version; extra == "dev"
Requires-Dist: docsig; extra == "dev"
Requires-Dist: no_implicit_optional; extra == "dev"
Requires-Dist: numpy==1.26.4; extra == "dev"
Requires-Dist: tensorflow==2.11.0; extra == "dev"
Requires-Dist: tensorflow_datasets; extra == "dev"
Requires-Dist: tensorflow_probability==0.19.0; extra == "dev"
Requires-Dist: timm; extra == "dev"
Requires-Dist: torch==1.13.1; extra == "dev"
Requires-Dist: torchvision==0.14.1; extra == "dev"
Provides-Extra: tensorflow-dev
Requires-Dist: mypy; extra == "tensorflow-dev"
Requires-Dist: ipywidgets; extra == "tensorflow-dev"
Requires-Dist: mkdocs-jupyter; extra == "tensorflow-dev"
Requires-Dist: mkdocstrings-python; extra == "tensorflow-dev"
Requires-Dist: flake8; extra == "tensorflow-dev"
Requires-Dist: setuptools; extra == "tensorflow-dev"
Requires-Dist: pre-commit; extra == "tensorflow-dev"
Requires-Dist: tox; extra == "tensorflow-dev"
Requires-Dist: black; extra == "tensorflow-dev"
Requires-Dist: ruff; extra == "tensorflow-dev"
Requires-Dist: ipython; extra == "tensorflow-dev"
Requires-Dist: ipykernel; extra == "tensorflow-dev"
Requires-Dist: pytest; extra == "tensorflow-dev"
Requires-Dist: pylint; extra == "tensorflow-dev"
Requires-Dist: mypy; extra == "tensorflow-dev"
Requires-Dist: mkdocs; extra == "tensorflow-dev"
Requires-Dist: mkdocs-material; extra == "tensorflow-dev"
Requires-Dist: mkdocstrings; extra == "tensorflow-dev"
Requires-Dist: mknotebooks; extra == "tensorflow-dev"
Requires-Dist: mike; extra == "tensorflow-dev"
Requires-Dist: bump2version; extra == "tensorflow-dev"
Requires-Dist: docsig; extra == "tensorflow-dev"
Requires-Dist: no_implicit_optional; extra == "tensorflow-dev"
Requires-Dist: numpy==1.26.4; extra == "tensorflow-dev"
Requires-Dist: tensorflow==2.11.0; extra == "tensorflow-dev"
Requires-Dist: tensorflow_datasets; extra == "tensorflow-dev"
Requires-Dist: tensorflow_probability==0.19.0; extra == "tensorflow-dev"
Provides-Extra: torch-dev
Requires-Dist: mypy; extra == "torch-dev"
Requires-Dist: ipywidgets; extra == "torch-dev"
Requires-Dist: mkdocs-jupyter; extra == "torch-dev"
Requires-Dist: mkdocstrings-python; extra == "torch-dev"
Requires-Dist: flake8; extra == "torch-dev"
Requires-Dist: setuptools; extra == "torch-dev"
Requires-Dist: pre-commit; extra == "torch-dev"
Requires-Dist: tox; extra == "torch-dev"
Requires-Dist: black; extra == "torch-dev"
Requires-Dist: ruff; extra == "torch-dev"
Requires-Dist: ipython; extra == "torch-dev"
Requires-Dist: ipykernel; extra == "torch-dev"
Requires-Dist: pytest; extra == "torch-dev"
Requires-Dist: pylint; extra == "torch-dev"
Requires-Dist: mypy; extra == "torch-dev"
Requires-Dist: mkdocs; extra == "torch-dev"
Requires-Dist: mkdocs-material; extra == "torch-dev"
Requires-Dist: mkdocstrings; extra == "torch-dev"
Requires-Dist: mknotebooks; extra == "torch-dev"
Requires-Dist: mike; extra == "torch-dev"
Requires-Dist: bump2version; extra == "torch-dev"
Requires-Dist: docsig; extra == "torch-dev"
Requires-Dist: no_implicit_optional; extra == "torch-dev"
Requires-Dist: numpy==1.26.4; extra == "torch-dev"
Requires-Dist: timm; extra == "torch-dev"
Requires-Dist: torch==1.13.1; extra == "torch-dev"
Requires-Dist: torchvision==0.14.1; extra == "torch-dev"
Provides-Extra: tensorflow
Requires-Dist: tensorflow==2.11.0; extra == "tensorflow"
Requires-Dist: tensorflow_datasets; extra == "tensorflow"
Requires-Dist: tensorflow_probability==0.19.0; extra == "tensorflow"
Provides-Extra: torch
Requires-Dist: timm; extra == "torch"
Requires-Dist: torch==1.13.1; extra == "torch"
Requires-Dist: torchvision==0.14.1; extra == "torch"
Provides-Extra: docs
Requires-Dist: mkdocs; extra == "docs"
Requires-Dist: mkdocs-material; extra == "docs"
Requires-Dist: mkdocstrings; extra == "docs"
Requires-Dist: mknotebooks; extra == "docs"
Requires-Dist: ipython; extra == "docs"
Dynamic: author
Dynamic: author-email
Dynamic: classifier
Dynamic: description
Dynamic: description-content-type
Dynamic: license-file
Dynamic: provides-extra
Dynamic: requires-dist
Dynamic: summary
